queuerPy/__init__.py
queuerPy/_version.py
queuerPy/py.typed
queuerPy/queuer.py
queuerPy/queuer_global.py
queuerPy/queuer_job.py
queuerPy/queuer_listener.py
queuerPy/queuer_master.py
queuerPy/queuer_next_interval.py
queuerPy/queuer_task.py
queuerPy/queuer_worker.py
queuerPy/core/__init__.py
queuerPy/core/broadcaster.py
queuerPy/core/listener.py
queuerPy/core/retryer.py
queuerPy/core/runner.py
queuerPy/core/scheduler.py
queuerPy/core/ticker.py
queuerPy/database/__init__.py
queuerPy/database/db_job.py
queuerPy/database/db_listener.py
queuerPy/database/db_master.py
queuerPy/database/db_worker.py
queuerPy/helper/__init__.py
queuerPy/helper/database.py
queuerPy/helper/error.py
queuerPy/helper/logging.py
queuerPy/helper/sql.py
queuerPy/helper/task.py
queuerPy/model/__init__.py
queuerPy/model/batch_job.py
queuerPy/model/connection.py
queuerPy/model/job.py
queuerPy/model/master.py
queuerPy/model/options.py
queuerPy/model/options_on_error.py
queuerPy/model/task.py
queuerPy/model/worker.py
queuerPy/sql/job.sql
queuerPy/sql/master.sql
queuerPy/sql/notify.sql
queuerPy/sql/worker.sql
queuerpy-0.19.0.dist-info/licenses/LICENSE
queuerpy-0.19.0.dist-info/METADATA
queuerpy-0.19.0.dist-info/WHEEL
queuerpy-0.19.0.dist-info/top_level.txt
queuerpy-0.19.0.dist-info/RECORD
