Metadata-Version: 2.4
Name: queuerPy
Version: 0.19.0
Summary: A Python implementation of the queuer system - a job queuing and processing system with PostgreSQL backend
Author-email: Simon Herrmann <siherrmann@users.noreply.github.com>
Maintainer-email: Simon Herrmann <siherrmann@users.noreply.github.com>
License-Expression: Apache-2.0
Project-URL: Homepage, https://github.com/siherrmann/queuerPy
Project-URL: Repository, https://github.com/siherrmann/queuerPy
Project-URL: Issues, https://github.com/siherrmann/queuerPy/issues
Project-URL: Documentation, https://github.com/siherrmann/queuerPy#readme
Keywords: queue,job,task,postgresql,worker,async
Classifier: Development Status :: 4 - Beta
Classifier: Intended Audience :: Developers
Classifier: Operating System :: OS Independent
Classifier: Programming Language :: Python :: 3
Classifier: Programming Language :: Python :: 3.8
Classifier: Programming Language :: Python :: 3.9
Classifier: Programming Language :: Python :: 3.10
Classifier: Programming Language :: Python :: 3.11
Classifier: Programming Language :: Python :: 3.12
Classifier: Topic :: Software Development :: Libraries :: Python Modules
Classifier: Topic :: System :: Distributed Computing
Classifier: Topic :: Database
Requires-Python: >=3.8
License-File: LICENSE
Requires-Dist: psycopg[binary]>=3.1.0
Provides-Extra: dev
Requires-Dist: pytest>=7.0.0; extra == "dev"
Requires-Dist: pytest-asyncio>=0.21.0; extra == "dev"
Requires-Dist: pytest-cov>=4.0.0; extra == "dev"
Requires-Dist: pytest-mock>=3.14.0; extra == "dev"
Requires-Dist: testcontainers[postgres]>=3.7.0; extra == "dev"
Requires-Dist: psutil>=5.8.0; extra == "dev"
Provides-Extra: test
Requires-Dist: pytest>=7.0.0; extra == "test"
Requires-Dist: pytest-asyncio>=0.21.0; extra == "test"
Requires-Dist: pytest-mock>=3.14.0; extra == "test"
Requires-Dist: testcontainers[postgres]>=3.7.0; extra == "test"
Requires-Dist: psutil>=5.8.0; extra == "test"
Dynamic: license-file
